[
    1,
    [
        "ecpdLyjvZBwrvm+cedCcQy",
        "d2j6WjUBlP8Y1TNMEMsP3u",
        "4eQzs4bqJDDrePAU06gRZy",
        "2d04sFV15PJau0kpbHzH3e",
        "d6eEkYWd9LMIRGoTpi3Uew"
    ],
    [
        "node",
        "_textureSetter",
        "_spriteFrame",
        "root",
        "data"
    ],
    [
        [
            "cc.Node",
            [
                "_name",
                "_components",
                "_prefab",
                "_contentSize",
                "_trs",
                "_parent",
                "_children",
                "_color"
            ],
            2,
            9,
            4,
            5,
            7,
            1,
            2,
            5
        ],
        [
            "cc.Sprite",
            [
                "_type",
                "_sizeMode",
                "node",
                "_materials",
                "_spriteFrame"
            ],
            1,
            1,
            3,
            6
        ],
        [
            "cc.Label",
            [
                "_string",
                "_styleFlags",
                "_N$verticalAlign",
                "_enableWrapText",
                "_N$overflow",
                "_N$horizontalAlign",
                "_fontSize",
                "_lineHeight",
                "node",
                "_materials"
            ],
            -5,
            1,
            3
        ],
        "cc.SpriteFrame",
        [
            "cc.PrefabInfo",
            [
                "fileId",
                "root",
                "asset"
            ],
            2,
            1,
            1
        ],
        [
            "cc.Prefab",
            [
                "_name"
            ],
            2
        ],
        [
            "667d7A3RhBATbef3r6wsxIf",
            [
                "node"
            ],
            3,
            1
        ]
    ],
    [
        [
            4,
            0,
            1,
            2,
            2
        ],
        [
            0,
            0,
            5,
            1,
            2,
            7,
            3,
            4,
            2
        ],
        [
            0,
            0,
            5,
            1,
            2,
            3,
            4,
            2
        ],
        [
            5,
            0,
            2
        ],
        [
            0,
            0,
            6,
            1,
            2,
            3,
            4,
            2
        ],
        [
            0,
            0,
            5,
            1,
            2,
            3,
            2
        ],
        [
            6,
            0,
            1
        ],
        [
            4,
            1,
            2,
            1
        ],
        [
            1,
            0,
            1,
            2,
            3,
            4,
            3
        ],
        [
            1,
            2,
            3,
            4,
            1
        ],
        [
            1,
            2,
            3,
            1
        ],
        [
            2,
            0,
            3,
            1,
            2,
            4,
            8,
            9,
            6
        ],
        [
            2,
            0,
            3,
            1,
            5,
            2,
            4,
            8,
            9,
            7
        ],
        [
            2,
            0,
            6,
            7,
            1,
            5,
            2,
            8,
            9,
            7
        ]
    ],
    [
        [
            [
                {
                    "name": "img_ph_jp1",
                    "rect": [
                        0,
                        0,
                        102,
                        134
                    ],
                    "offset": [
                        0,
                        0
                    ],
                    "originalSize": [
                        102,
                        134
                    ],
                    "capInsets": [
                        0,
                        0,
                        0,
                        0
                    ]
                }
            ],
            [
                3
            ],
            0,
            [
                0
            ],
            [
                1
            ],
            [
                1
            ]
        ],
        [
            [
                [
                    3,
                    "rankItem"
                ],
                [
                    4,
                    "rankItem",
                    [
                        -3,
                        -4,
                        -5,
                        -6,
                        -7,
                        -8
                    ],
                    [
                        [
                            6,
                            -2
                        ]
                    ],
                    [
                        7,
                        -1,
                        0
                    ],
                    [
                        5,
                        900,
                        150
                    ],
                    [
                        0,
                        -117.947,
                        0,
                        0,
                        0,
                        0,
                        1,
                        1,
                        1,
                        1
                    ]
                ],
                [
                    5,
                    "rankBg",
                    1,
                    [
                        [
                            8,
                            1,
                            0,
                            -9,
                            [
                                0
                            ],
                            1
                        ]
                    ],
                    [
                        0,
                        "fciOC5CstOvaLuspXXCFPF",
                        1,
                        0
                    ],
                    [
                        5,
                        894.4,
                        150
                    ]
                ],
                [
                    2,
                    "rankIcon",
                    1,
                    [
                        [
                            9,
                            -10,
                            [
                                2
                            ],
                            3
                        ]
                    ],
                    [
                        0,
                        "3cky1/CT9LaqtYiD/WbQ7M",
                        1,
                        0
                    ],
                    [
                        5,
                        102,
                        134
                    ],
                    [
                        -320,
                        0,
                        0,
                        0,
                        0,
                        0,
                        1,
                        1,
                        1,
                        1
                    ]
                ],
                [
                    1,
                    "nickName",
                    1,
                    [
                        [
                            11,
                            "Label",
                            false,
                            1,
                            1,
                            1,
                            -11,
                            [
                                4
                            ]
                        ]
                    ],
                    [
                        0,
                        "e94VxoLvJJSbwSeqoaj75A",
                        1,
                        0
                    ],
                    [
                        4,
                        4279189083
                    ],
                    [
                        5,
                        300,
                        100
                    ],
                    [
                        54.54,
                        0,
                        0,
                        0,
                        0,
                        0,
                        1,
                        1,
                        1,
                        1
                    ]
                ],
                [
                    1,
                    "scoreLabel",
                    1,
                    [
                        [
                            12,
                            "Label",
                            false,
                            1,
                            2,
                            1,
                            1,
                            -12,
                            [
                                5
                            ]
                        ]
                    ],
                    [
                        0,
                        "91YbkTKYpK4bBW72Rv3TAg",
                        1,
                        0
                    ],
                    [
                        4,
                        4279189083
                    ],
                    [
                        5,
                        200,
                        100
                    ],
                    [
                        321.866,
                        0,
                        0,
                        0,
                        0,
                        0,
                        1,
                        1,
                        1,
                        1
                    ]
                ],
                [
                    2,
                    "avater",
                    1,
                    [
                        [
                            10,
                            -13,
                            [
                                6
                            ]
                        ]
                    ],
                    [
                        0,
                        "686SIj7CZJO5Tlru7S5wQ9",
                        1,
                        0
                    ],
                    [
                        5,
                        100,
                        100
                    ],
                    [
                        -181.942,
                        0,
                        0,
                        0,
                        0,
                        0,
                        1,
                        0.8,
                        0.8,
                        1
                    ]
                ],
                [
                    1,
                    "rank",
                    1,
                    [
                        [
                            13,
                            "1",
                            60,
                            60,
                            1,
                            1,
                            1,
                            -14,
                            [
                                7
                            ]
                        ]
                    ],
                    [
                        0,
                        "0fPdaF1WhPxKxs32Vb3yhD",
                        1,
                        0
                    ],
                    [
                        4,
                        4279189083
                    ],
                    [
                        5,
                        33.37,
                        75.6
                    ],
                    [
                        -320,
                        0,
                        0,
                        0,
                        0,
                        0,
                        1,
                        1,
                        1,
                        1
                    ]
                ]
            ],
            0,
            [
                0,
                3,
                1,
                0,
                0,
                1,
                0,
                -1,
                2,
                0,
                -2,
                3,
                0,
                -3,
                4,
                0,
                -4,
                5,
                0,
                -5,
                6,
                0,
                -6,
                7,
                0,
                0,
                2,
                0,
                0,
                3,
                0,
                0,
                4,
                0,
                0,
                5,
                0,
                0,
                6,
                0,
                0,
                7,
                0,
                4,
                1,
                14
            ],
            [
                0,
                0,
                0,
                0,
                0,
                0,
                0,
                0
            ],
            [
                -1,
                2,
                -1,
                2,
                -1,
                -1,
                -1,
                -1
            ],
            [
                0,
                2,
                0,
                3,
                0,
                0,
                0,
                0
            ]
        ],
        [
            [
                {
                    "name": "img_ph_dk1",
                    "rect": [
                        0,
                        0,
                        688,
                        150
                    ],
                    "offset": [
                        0,
                        0
                    ],
                    "originalSize": [
                        688,
                        150
                    ],
                    "capInsets": [
                        0,
                        0,
                        0,
                        0
                    ]
                }
            ],
            [
                3
            ],
            0,
            [
                0
            ],
            [
                1
            ],
            [
                4
            ]
        ]
    ]
]